producthunt_sdk/__init__.py
producthunt_sdk/auth.py
producthunt_sdk/client.py
producthunt_sdk/exceptions.py
producthunt_sdk/models.py
producthunt_sdk/queries.py
producthunt_sdk/rate_limiter.py
producthunt_sdk-0.2.0.dist-info/METADATA
producthunt_sdk-0.2.0.dist-info/WHEEL
producthunt_sdk-0.2.0.dist-info/licenses/LICENSE
producthunt_sdk-0.2.0.dist-info/RECORD
