Metadata-Version: 2.4
Name: producthunt-sdk
Version: 0.2.0
Summary: Python SDK for the Product Hunt API v2
License-File: LICENSE
Requires-Python: >=3.13
Requires-Dist: httpx>=0.27.0
Requires-Dist: pydantic>=2.0.0
Requires-Dist: tenacity>=9.1.2
Provides-Extra: dev
Requires-Dist: pytest-asyncio>=0.24.0; extra == 'dev'
Requires-Dist: pytest>=8.0.0; extra == 'dev'
Requires-Dist: ruff>=0.8.0; extra == 'dev'
Provides-Extra: examples
Requires-Dist: python-dotenv>=1.0.0; extra == 'examples'
